MANIFEST.in
README.rst
setup.py
tls_property.py
tls_property.egg-info/PKG-INFO
tls_property.egg-info/SOURCES.txt
tls_property.egg-info/dependency_links.txt
tls_property.egg-info/requires.txt
tls_property.egg-info/top_level.txt